igym/__init__.py
igym/seeding.py
igym-0.0.2.dist-info/LICENSE
igym-0.0.2.dist-info/METADATA
igym-0.0.2.dist-info/WHEEL
igym-0.0.2.dist-info/top_level.txt
igym-0.0.2.dist-info/RECORD
