Metadata-Version: 2.1
Name: igym
Version: 0.0.2
Summary: Gym for your AI to connect with the internet and play around.
Home-page: https://github.com/yashbonde/igym
Author: Yash Bonde
Author-email: bonde.yash97@gmail.com
License: UNKNOWN
Project-URL: Bug Tracker, https://github.com/yashbonde/igym/issues
Platform: UNKNOWN
Classifier: Programming Language :: Python :: 3
Classifier: License :: OSI Approved :: MIT License
Classifier: Operating System :: OS Independent
Requires-Python: >=3.6
